<?xml version="1.0" encoding="UTF-8"?>
<objects serializationModel="Studio.02.03.00">
	<object class="AudioFile" id="{d0ed960d-ee1d-4a0c-a690-7331efd0935a}">
		<property name="assetPath">
			<value>Designed, Impact, Fire, Sparkles, Whoosh SND112599.wav</value>
		</property>
		<property name="frequencyInKHz">
			<value>48</value>
		</property>
		<property name="channelCount">
			<value>2</value>
		</property>
		<property name="length">
			<value>0.87422916666666661</value>
		</property>
		<relationship name="masterAssetFolder">
			<destination>{e5e3d7d2-e8ec-47c2-b9e9-507161cf1239}</destination>
		</relationship>
	</object>
</objects>
